{"singlePage": [], "startSite": "11/24/2024", "filingNum": "", "onePageListNum": 15, "commentLabelColor": "#006b75", "yearColorList": ["#bc4c00", "#0969da", "#1f883d", "#A333D0"], "i18n": "CN", "themeMode": "manual", "dayTheme": "light", "nightTheme": "dark", "urlMode": "pinyin", "script": "<script src='https://blog.meekdai.com/Gmeek/plugins/GmeekTOC.js'></script><script src='https://blog.meekdai.com/Gmeek/plugins/lightbox.js'></script>", "style": "", "head": "", "indexScript": "", "indexStyle": "", "bottomText": "Have a good day", "showPostSource": 1, "iconList": {"ac": "M8 4a4 4 0 1 1 0 8 4 4 0 0 1 0-8Z"}, "UTC": 8, "rssSplit": "sentence", "exlink": {"ac": "https://ac.shameless.top"}, "needComment": 1, "allHead": "<script src='https://blog.meekdai.com/Gmeek/plugins/GmeekVercount.js'></script>", "title": "Todo Notes", "subTitle": "Record personal todo list daily", "avatarUrl": "https://aea62e6.webp.li/2024/11/favicon.png", "displayTitle": "Shameless", "homeUrl": "https://todo.shameless.top", "ogImage": "", "primerCSS": "<link href='https://mirrors.sustech.edu.cn/cdnjs/ajax/libs/Primer/21.0.7/primer.css' rel='stylesheet' />", "GMEEK_VERSION": "last", "postListJson": {"P1": {"htmlDir": "docs/post/example test.html", "labels": ["documentation"], "postTitle": "example test", "postUrl": "post/example%20test.html", "postSourceUrl": "https://github.com/acshameless/acshameless.github.io/issues/1", "commentNum": 0, "wordCount": 5, "description": "## Hi\u3002", "top": 0, "createdAt": 1732466763, "style": "", "script": "<script src='https://blog.meekdai.com/Gmeek/plugins/GmeekTOC.js'></script><script src='https://blog.meekdai.com/Gmeek/plugins/lightbox.js'></script>", "head": "", "ogImage": "", "createdDate": "2024-11-25", "dateLabelColor": "#bc4c00"}, "P2": {"htmlDir": "docs/post/W47-2024 -kan-wan-shi-tian-ru-men-qian-duan-bing-ji-lu.html", "labels": ["Todo"], "postTitle": "W47-2024 \u770b\u5b8c\u5341\u5929\u5165\u95e8\u524d\u7aef\u5e76\u8bb0\u5f55", "postUrl": "post/W47-2024%20-kan-wan-shi-tian-ru-men-qian-duan-bing-ji-lu.html", "postSourceUrl": "https://github.com/acshameless/acshameless.github.io/issues/2", "commentNum": 1, "wordCount": 43, "description": "https://www.bilibili.com/video/BV1Yp421d7oZ\u3002", "top": 0, "createdAt": 1732468271, "style": "", "script": "<script src='https://blog.meekdai.com/Gmeek/plugins/GmeekTOC.js'></script><script src='https://blog.meekdai.com/Gmeek/plugins/lightbox.js'></script>", "head": "", "ogImage": "", "createdDate": "2024-11-25", "dateLabelColor": "#bc4c00"}, "P3": {"htmlDir": "docs/post/W50-2024 -kan-wan- SAA -shi-pin.html", "labels": ["Todo"], "postTitle": "W50-2024 \u770b\u5b8c SAA \u89c6\u9891", "postUrl": "post/W50-2024%20-kan-wan-%20SAA%20-shi-pin.html", "postSourceUrl": "https://github.com/acshameless/acshameless.github.io/issues/3", "commentNum": 1, "wordCount": 96, "description": "1. https://www.bilibili.com/video/BV1wR4y1F7YM/\r\n2. https://www.bilibili.com/video/BV16L4y177kj/\u3002", "top": 0, "createdAt": 1733761983, "style": "", "script": "<script src='https://blog.meekdai.com/Gmeek/plugins/GmeekTOC.js'></script><script src='https://blog.meekdai.com/Gmeek/plugins/lightbox.js'></script>", "head": "", "ogImage": "", "createdDate": "2024-12-10", "dateLabelColor": "#bc4c00"}, "P4": {"htmlDir": "docs/post/W50-2024 -wei-guan- Pycon -shi-pin.html", "labels": ["Todo"], "postTitle": "W50-2024 \u56f4\u89c2 Pycon \u89c6\u9891", "postUrl": "post/W50-2024%20-wei-guan-%20Pycon%20-shi-pin.html", "postSourceUrl": "https://github.com/acshameless/acshameless.github.io/issues/4", "commentNum": 0, "wordCount": 43, "description": "https://www.bilibili.com/video/BV19Qz9YLEMR\u3002", "top": 0, "createdAt": 1734193390, "style": "", "script": "<script src='https://blog.meekdai.com/Gmeek/plugins/GmeekTOC.js'></script><script src='https://blog.meekdai.com/Gmeek/plugins/lightbox.js'></script>", "head": "", "ogImage": "", "createdDate": "2024-12-15", "dateLabelColor": "#bc4c00"}, "P5": {"htmlDir": "docs/post/W50-2024 -kan-wan- SAP -shi-pin.html", "labels": ["Todo"], "postTitle": "W50-2024 \u770b\u5b8c SAP \u89c6\u9891", "postUrl": "post/W50-2024%20-kan-wan-%20SAP%20-shi-pin.html", "postSourceUrl": "https://github.com/acshameless/acshameless.github.io/issues/5", "commentNum": 0, "wordCount": 43, "description": "https://www.bilibili.com/video/BV1BY4y1Q7k1\u3002", "top": 0, "createdAt": 1734193471, "style": "", "script": "<script src='https://blog.meekdai.com/Gmeek/plugins/GmeekTOC.js'></script><script src='https://blog.meekdai.com/Gmeek/plugins/lightbox.js'></script>", "head": "", "ogImage": "", "createdDate": "2024-12-15", "dateLabelColor": "#bc4c00"}, "P6": {"htmlDir": "docs/post/W51-2024 -kan-wan- CS50 -shi-pin.html", "labels": ["Todo"], "postTitle": "W51-2024 \u770b\u5b8c CS50 \u89c6\u9891", "postUrl": "post/W51-2024%20-kan-wan-%20CS50%20-shi-pin.html", "postSourceUrl": "https://github.com/acshameless/acshameless.github.io/issues/6", "commentNum": 0, "wordCount": 43, "description": "https://www.bilibili.com/video/BV1cWpgemEDo\u3002", "top": 0, "createdAt": 1735145664, "style": "", "script": "<script src='https://blog.meekdai.com/Gmeek/plugins/GmeekTOC.js'></script><script src='https://blog.meekdai.com/Gmeek/plugins/lightbox.js'></script>", "head": "", "ogImage": "", "createdDate": "2024-12-26", "dateLabelColor": "#bc4c00"}, "P7": {"htmlDir": "docs/post/25W01--ting-ge.html", "labels": ["music"], "postTitle": "25W01-\u542c\u6b4c", "postUrl": "post/25W01--ting-ge.html", "postSourceUrl": "https://github.com/acshameless/acshameless.github.io/issues/7", "commentNum": 0, "wordCount": 46, "description": "1. https://www.bilibili.com/video/BV1vMrwY6EKw\u3002", "top": 0, "createdAt": 1735997341, "style": "", "script": "<script src='https://blog.meekdai.com/Gmeek/plugins/GmeekTOC.js'></script><script src='https://blog.meekdai.com/Gmeek/plugins/lightbox.js'></script>", "head": "", "ogImage": "", "createdDate": "2025-01-04", "dateLabelColor": "#0969da"}, "P8": {"htmlDir": "docs/post/ALL--cheng-wei-yi-ge-you-mu-biao-de-xue-xi-zhe.html", "labels": ["documentation"], "postTitle": "ALL-\u6210\u4e3a\u4e00\u4e2a\u6709\u76ee\u6807\u7684\u5b66\u4e60\u8005", "postUrl": "post/ALL--cheng-wei-yi-ge-you-mu-biao-de-xue-xi-zhe.html", "postSourceUrl": "https://github.com/acshameless/acshameless.github.io/issues/8", "commentNum": 0, "wordCount": 1938, "description": "\u8f6c\u8f7d\u81ea https://daimajia.com/2017/02/25/you-need-a-goal/\r\n> \u6211\u4e00\u4e2a\u597d\u670b\u53cb\uff0c\u4ed6\u5728\u4e00\u5bb6\u56fd\u5185\u8f83\u5927\u501f\u8d37\u5e73\u53f0\u505a\u524d\u7aef\u5de5\u7a0b\u5e08\uff0c\u6bcf\u5929\u4e94\u70b9\u8d77\u5e8a\uff0c\u65e9\u65e9\u7684\u5230\u516c\u53f8\uff0c\u5f00\u59cb\u8bfb\u4e00\u4e9b\u7ecf\u5178\u7684\u524d\u7aef\u7c7b\u7684\u4e66\u7c4d\u3002", "top": 0, "createdAt": 1736063399, "style": "", "script": "<script src='https://blog.meekdai.com/Gmeek/plugins/GmeekTOC.js'></script><script src='https://blog.meekdai.com/Gmeek/plugins/lightbox.js'></script>", "head": "", "ogImage": "", "createdDate": "2025-01-05", "dateLabelColor": "#0969da"}, "P9": {"htmlDir": "docs/post/25W05--kan-wan- Linux -shi-pin.html", "labels": ["Todo"], "postTitle": "25W05-\u770b\u5b8c Linux \u89c6\u9891", "postUrl": "post/25W05--kan-wan-%20Linux%20-shi-pin.html", "postSourceUrl": "https://github.com/acshameless/acshameless.github.io/issues/9", "commentNum": 0, "wordCount": 310, "description": "1. https://www.bilibili.com/video/BV1nz4y1C7uY\n2. https://www.bilibili.com/video/BV1654y167np\n3. https://www.bilibili.com/video/BV12f4y1Y7eQ\n4. https://www.bilibili.com/video/BV1uz4y1y7EA\n5. https://www.bilibili.com/list/watchlater?bvid=BV1gy4y1p7AX&oid=801289234\n6. https://www.bilibili.com/video/BV1s54y1p7eE\u3002", "top": 0, "createdAt": 1738490879, "style": "", "script": "<script src='https://blog.meekdai.com/Gmeek/plugins/GmeekTOC.js'></script><script src='https://blog.meekdai.com/Gmeek/plugins/lightbox.js'></script>", "head": "", "ogImage": "", "createdDate": "2025-02-02", "dateLabelColor": "#0969da"}}, "singeListJson": {}, "labelColorDict": {"bug": "#d73a4a", "documentation": "#0075ca", "duplicate": "#cfd3d7", "enhancement": "#a2eeef", "good first issue": "#7057ff", "help wanted": "#008672", "invalid": "#e4e669", "music": "#7C08AD", "question": "#d876e3", "Todo": "#57FEE1", "wontfix": "#ffffff"}, "faviconUrl": "https://aea62e6.webp.li/2024/11/favicon.png", "prevUrl": "disabled", "nextUrl": "disabled"}